pyapes/__init__.py
pyapes/backend.py
pyapes/geometry/__init__.py
pyapes/geometry/basis.py
pyapes/geometry/box.py
pyapes/geometry/cylinder.py
pyapes/mesh/__init__.py
pyapes/mesh/_mesh.py
pyapes/mesh/tools.py
pyapes/runner.py
pyapes/solver/__init__.py
pyapes/solver/fdc.py
pyapes/solver/fdm.py
pyapes/solver/linalg.py
pyapes/solver/ops.py
pyapes/solver/rfp.py
pyapes/solver/tools.py
pyapes/solver/types.py
pyapes/testing/__init__.py
pyapes/testing/burgers.py
pyapes/testing/poisson.py
pyapes/variables/__init__.py
pyapes/variables/bcs.py
pyapes/variables/container.py
pyapes/variables/fields.py
pyapes-0.2.13.dist-info/WHEEL
pyapes-0.2.13.dist-info/METADATA
pyapes-0.2.13.dist-info/RECORD
