Metadata-Version: 2.1
Name: pyapes
Version: 0.2.13
Summary: Python Awesome Partial differential Equation Solver
Author: Kyoungseoun Chung
Author-email: kchung@student.ethz.ch
Requires-Python: >=3.10,<3.12
Classifier: Programming Language :: Python :: 3
Classifier: Programming Language :: Python :: 3.10
Requires-Dist: pymyplot (>=0.2.7,<0.3.0)
Requires-Dist: pymytools (>=0.1.15,<0.2.0)
Requires-Dist: torch (>=2.0.0,<3.0.0); sys_platform == "darwin"
Requires-Dist: torch (>=2.0.0,<3.0.0); sys_platform == "win32"
